mathstring/__init__.py
mathstring/calculator.py
mathstring-0.1.0.dist-info/licenses/LICENSE.md
mathstring-0.1.0.dist-info/METADATA
mathstring-0.1.0.dist-info/WHEEL
mathstring-0.1.0.dist-info/top_level.txt
mathstring-0.1.0.dist-info/RECORD
