Metadata-Version: 2.4
Name: mathstring
Version: 0.1.0
Summary: English:
Home-page: https://github.com/ryan-alsaidani/mathstring
Author: Ryan Alsaidani
Author-email: Ryan Alsaidani <ryan.alsaidani@gmail.com>
Project-URL: Homepage, https://github.com/ryan-alsaidani/mathstring
Project-URL: Repository, https://github.com/ryan-alsaidani/mathstring
Project-URL: BugTracker, https://github.com/ryan-alsaidani/mathstring/issues
Keywords: calculator,math,equations,text processing,python
Classifier: Development Status :: 4 - Beta
Classifier: Intended Audience :: Developers
Classifier: Topic :: Software Development :: Libraries
Classifier: Topic :: Scientific/Engineering :: Mathematics
Classifier: Topic :: Utilities
Classifier: Topic :: Education
Classifier: Programming Language :: Python :: 3
Classifier: Programming Language :: Python :: 3.7
Classifier: Programming Language :: Python :: 3.8
Classifier: Programming Language :: Python :: 3.9
Classifier: Programming Language :: Python :: 3.10
Classifier: Programming Language :: Python :: Implementation :: CPython
Classifier: Natural Language :: Arabic
Classifier: Operating System :: OS Independent
Requires-Python: >=3.7
License-File: LICENSE.md
Dynamic: author
Dynamic: home-page
Dynamic: license-file
Dynamic: requires-python
